{
  "timestamp": "2025-11-24T03:37:40.030386+00:00",
  "total_changes": 0,
  "categories": [
    {
      "name": "Media supplied by Universitätsarchiv St. Gallen",
      "label": "HSG",
      "report_directory": "reports/HSG Archiv/2025-10_20251124_033915_[0]",
      "changes": 0
    },
    {
      "name": "Rahn Collection",
      "label": "Rahn",
      "report_directory": "reports/Rahn Collection/2025-10_20251124_034259_[0]",
      "changes": 0
    },
    {
      "name": "Breitinger Collection",
      "label": "Breitinger",
      "report_directory": "reports/Breitinger Collection/2025-10_20251124_034618_[0]",
      "changes": 0
    },
    {
      "name": "Steinfels Collection",
      "label": "Steinfels",
      "report_directory": "reports/Steinfels Collection/2025-10_20251124_034856_[0]",
      "changes": 0
    }
  ]
}